LICENSE
MANIFEST.in
README.md
requirements.txt
setup.cfg
setup.py
test_requirements.txt
django_familytree.egg-info/PKG-INFO
django_familytree.egg-info/SOURCES.txt
django_familytree.egg-info/dependency_links.txt
django_familytree.egg-info/namespace_packages.txt
django_familytree.egg-info/not-zip-safe
django_familytree.egg-info/requires.txt
django_familytree.egg-info/top_level.txt
familytree/__init__.py
familytree/admin.py
familytree/models.py
familytree/signals.py
familytree/templatetags/__init__.py
familytree/templatetags/familytree_tags.py