Metadata-Version: 1.1
Name: django-familytree
Version: 0.0.2
Summary: Familytree application for django
Home-page: https://github.com/rocktavious/django-familytree
Author: Kyle Rockman
Author-email: kyle.rockman@mac.com
License: The MIT License (MIT)
